MANIFEST.in
README.md
requirements.txt
setup.py
./NNDensity/_kd_tree.c
./NNDensity/_partition_nodes.cpp
C:/ProgramData/Anaconda3/lib/site-packages/numpy/core/include/numpy/arrayobject.h
C:/ProgramData/Anaconda3/lib/site-packages/numpy/core/include/numpy/ufuncobject.h
NNDensity/_NNDE.py
NNDensity/__init__.py
NNDensity/_distributions.py
NNDensity/_kd_tree.c
NNDensity/_partition_nodes.cpp
NNDensity/_utils.py
NNDensity/_visualization.py
NNDensity.egg-info/PKG-INFO
NNDensity.egg-info/SOURCES.txt
NNDensity.egg-info/dependency_links.txt
NNDensity.egg-info/requires.txt
NNDensity.egg-info/top_level.txt