Metadata-Version: 2.1
Name: NNDensity
Version: 0.0.3
Summary: Nearest Neighbor Density Estimation
Home-page: https://github.com/Karlmyh/NNDensity
Author: Yuheng Ma
Author-email: yma@ruc.edu.cn
Requires-Python: >=3
